ticca/__init__.py
ticca/__main__.py
ticca/callbacks.py
ticca/claude_cache_client.py
ticca/config.py
ticca/http_utils.py
ticca/hybrid_storage.py
ticca/main.py
ticca/model_factory.py
ticca/models.json
ticca/perf.py
ticca/reopenable_async_client.py
ticca/round_robin_model.py
ticca/session_storage.py
ticca/status_display.py
ticca/summarization_agent.py
ticca/tui_state.py
ticca/version_checker.py
ticca/agents/__init__.py
ticca/agents/agent_code_agent.py
ticca/agents/agent_code_reviewer.py
ticca/agents/agent_manager.py
ticca/agents/agent_planning.py
ticca/agents/agent_qa_agent.py
ticca/agents/agent_security_auditor.py
ticca/agents/base_agent.py
ticca/agents/json_agent.py
ticca/command_line/__init__.py
ticca/command_line/attachments.py
ticca/command_line/command_handler.py
ticca/command_line/command_registry.py
ticca/command_line/config_commands.py
ticca/command_line/core_commands.py
ticca/command_line/file_path_completion.py
ticca/command_line/load_context_completion.py
ticca/command_line/mcp_completion.py
ticca/command_line/model_picker_completion.py
ticca/command_line/motd.py
ticca/command_line/pin_command_completion.py
ticca/command_line/prompt_toolkit_completion.py
ticca/command_line/session_commands.py
ticca/command_line/utils.py
ticca/command_line/mcp/__init__.py
ticca/command_line/mcp/add_command.py
ticca/command_line/mcp/base.py
ticca/command_line/mcp/handler.py
ticca/command_line/mcp/help_command.py
ticca/command_line/mcp/install_command.py
ticca/command_line/mcp/list_command.py
ticca/command_line/mcp/logs_command.py
ticca/command_line/mcp/remove_command.py
ticca/command_line/mcp/restart_command.py
ticca/command_line/mcp/search_command.py
ticca/command_line/mcp/start_all_command.py
ticca/command_line/mcp/start_command.py
ticca/command_line/mcp/status_command.py
ticca/command_line/mcp/stop_all_command.py
ticca/command_line/mcp/stop_command.py
ticca/command_line/mcp/test_command.py
ticca/command_line/mcp/utils.py
ticca/command_line/mcp/wizard_utils.py
ticca-0.2.0.dist-info/METADATA
ticca-0.2.0.dist-info/WHEEL
ticca-0.2.0.dist-info/entry_points.txt
ticca-0.2.0.dist-info/licenses/LICENSE
ticca-0.2.0.dist-info/RECORD
