Metadata-Version: 2.4
Name: ticca
Version: 0.2.0
Summary: Terminal Injected Coding CLI Assistant
Project-URL: repository, https://github.com/janfeddersen-wq/ticca
Project-URL: HomePage, https://github.com/janfeddersen-wq/ticca
Author: Michael Pfaffenberger
License: MIT
License-File: LICENSE
Classifier: License :: OSI Approved :: MIT License
Classifier: Operating System :: OS Independent
Classifier: Programming Language :: Python :: 3
Classifier: Programming Language :: Python :: 3.11
Classifier: Programming Language :: Python :: 3.12
Classifier: Programming Language :: Python :: 3.13
Classifier: Topic :: Software Development :: Code Generators
Requires-Python: <3.14,>=3.11
Requires-Dist: bs4>=0.0.2
Requires-Dist: camoufox>=0.4.11
Requires-Dist: chromadb>=0.5.0
Requires-Dist: dbos>=2.0.0
Requires-Dist: fastapi>=0.110.0
Requires-Dist: gac>=0.1.0
Requires-Dist: httpx-limiter>=0.3.0
Requires-Dist: httpx[http2]>=0.24.1
Requires-Dist: json-repair>=0.46.2
Requires-Dist: logfire>=0.7.1
Requires-Dist: openai>=1.99.1
Requires-Dist: pathspec>=0.11.0
Requires-Dist: pillow>=10.0.0
Requires-Dist: playwright>=1.40.0
Requires-Dist: prompt-toolkit>=3.0.52
Requires-Dist: pydantic-ai==1.0.5
Requires-Dist: pydantic>=2.4.0
Requires-Dist: pyfiglet>=0.8.post1
Requires-Dist: pyjwt>=2.8.0
Requires-Dist: pytest-cov>=6.1.1
Requires-Dist: python-dotenv>=1.0.0
Requires-Dist: rapidfuzz>=3.13.0
Requires-Dist: rich>=13.4.2
Requires-Dist: ripgrep==14.1.0
Requires-Dist: ruff>=0.11.11
Requires-Dist: sentence-transformers>=2.2.0
Requires-Dist: tenacity>=8.2.0
Requires-Dist: termcolor>=3.1.0
Requires-Dist: textual-dev>=1.7.0
Requires-Dist: textual[syntax]>=5.0.0
Requires-Dist: uvicorn>=0.29.0
